meta_form_validators/__init__.py
meta_form_validators/apps.py
meta_form_validators/models.py
meta_form_validators/tests.py
meta_form_validators/form_validators/__init__.py
meta_form_validators/form_validators/subject_consent.py
meta_form_validators/form_validators/blood_results/__init__.py
meta_form_validators/form_validators/blood_results/blood_results_form_validator.py
meta_form_validators/form_validators/blood_results/blood_results_form_validator_mixin.py
meta_form_validators/tests/__init__.py
meta_form_validators/tests/test_form_validators.py
meta_form_validators/tests/urls.py
meta_form_validators-0.1.10.dist-info/AUTHORS
meta_form_validators-0.1.10.dist-info/LICENSE
meta_form_validators-0.1.10.dist-info/METADATA
meta_form_validators-0.1.10.dist-info/WHEEL
meta_form_validators-0.1.10.dist-info/top_level.txt
meta_form_validators-0.1.10.dist-info/RECORD
